yt_dlp_host_api/__init__.py
yt_dlp_host_api/api.py
yt_dlp_host_api/client.py
yt_dlp_host_api/exceptions.py
yt_dlp_host_api/task.py
yt_dlp_host_api-0.2.1.dist-info/licenses/LICENSE
yt_dlp_host_api-0.2.1.dist-info/METADATA
yt_dlp_host_api-0.2.1.dist-info/WHEEL
yt_dlp_host_api-0.2.1.dist-info/top_level.txt
yt_dlp_host_api-0.2.1.dist-info/RECORD
