Metadata-Version: 2.4
Name: yt_dlp_host_api
Version: 0.2.1
Summary: A Python library for interacting with the yt-dlp-host API
Author-email: "Amadeus (Wasys)" <tubik.corp@gmail.com>
License-Expression: MIT
Project-URL: Homepage, https://github.com/Vasysik/yt-dlp-host-api
Project-URL: Issues, https://github.com/Vasysik/yt-dlp-host-api/issues
Classifier: Programming Language :: Python :: 3
Classifier: Operating System :: OS Independent
Requires-Python: >=3.8
License-File: LICENSE
Requires-Dist: requests>=2.25.1
Dynamic: license-file
